pyrap/__init__.py
pyrap/__main__.py
pyrap/pyrap.py
pyrap/ui.py
pyrap-0.0.5.dist-info/METADATA
pyrap-0.0.5.dist-info/RECORD
pyrap-0.0.5.dist-info/WHEEL
pyrap-0.0.5.dist-info/entry_points.txt
pyrap-0.0.5.dist-info/top_level.txt
