Metadata-Version: 2.1
Name: pyrap
Version: 0.0.5
Summary: Rsync Wrapper to Backup/Restore all Users.
Home-page: https://github.com/tslight/pyrap
Author: Toby Slight
Author-email: tobyslight@gmail.com
License: UNKNOWN
Platform: UNKNOWN
Classifier: Programming Language :: Python :: 3
Classifier: License :: OSI Approved :: BSD License
Classifier: Operating System :: OS Independent
